negogv_log/__init__.py
negogv_log/logger.py
negogv_log-0.1.2.dist-info/licenses/LICENSE
negogv_log-0.1.2.dist-info/METADATA
negogv_log-0.1.2.dist-info/WHEEL
negogv_log-0.1.2.dist-info/top_level.txt
negogv_log-0.1.2.dist-info/RECORD
