Metadata-Version: 2.4
Name: negogv-log
Version: 0.1.2
Summary: A custom Python logger configuration with colored console output.
Author-email: Daniel Weber <pochta.danila2@gmail.com>
License: MIT License
Project-URL: Homepage, https://github.com/negogv/negogv_logger
Classifier: Programming Language :: Python :: 3
Classifier: License :: OSI Approved :: MIT License
Classifier: Operating System :: OS Independent
Requires-Python: >=3.6
License-File: LICENSE
Dynamic: license-file
